{"entityType":"lead","fileName":"LEAD_20260514_90c5776f_6a06265e40ad6.csv","sourceLabel":"bitrix-leads-hard-2026-05-15","dedupPolicy":"update","rows":[{"id":29926,"createdAt":1712943751000,"contactName":"7 905 117-88-27 - Входящий звонок","contactPhone":"79051178827","contactCompany":null,"requestedDate":null,"address":null,"comment":"","source":"mango","equipmentTypeHint":null,"isUrgent":false,"externalSourceId":"bitrix-lead-29926"},{"id":29922,"createdAt":1712932384000,"contactName":"7 499 266-42-82 - Входящий звонок","contactPhone":"74992664282","contactCompany":null,"requestedDate":null,"address":null,"comment":"","source":"mango","equipmentTypeHint":null,"isUrgent":false,"externalSourceId":"bitrix-lead-29922"},{"id":29920,"createdAt":1712930460000,"contactName":"7 916 545-50-50 - Входящий звонок","contactPhone":"79165455050","contactCompany":null,"requestedDate":null,"address":null,"comment":"","source":"mango","equipmentTypeHint":null,"isUrgent":false,"externalSourceId":"bitrix-lead-29920"},{"id":29918,"createdAt":1712930242000,"contactName":"7 985 063-37-57 - Исходящий звонок","contactPhone":"79850633757","contactCompany":null,"requestedDate":null,"address":null,"comment":"","source":"mango","equipmentTypeHint":null,"isUrgent":false,"externalSourceId":"bitrix-lead-29918"},{"id":29914,"createdAt":1712926441000,"contactName":"7 906 772-27-27 - Входящий звонок","contactPhone":"79067722727","contactCompany":null,"requestedDate":null,"address":null,"comment":"","source":"mango","equipmentTypeHint":null,"isUrgent":false,"externalSourceId":"bitrix-lead-29914"},{"id":29912,"createdAt":1712925050000,"contactName":"7 985 228-41-88 - Входящий звонок","contactPhone":"79852284188","contactCompany":null,"requestedDate":null,"address":null,"comment":"","source":"mango","equipmentTypeHint":null,"isUrgent":false,"externalSourceId":"bitrix-lead-29912"},{"id":29908,"createdAt":1712921090000,"contactName":"7 925 098-89-11 - Входящий звонок","contactPhone":"79250988911","contactCompany":null,"requestedDate":null,"address":null,"comment":"","source":"mango","equipmentTypeHint":null,"isUrgent":false,"externalSourceId":"bitrix-lead-29908"},{"id":29906,"createdAt":1712920180000,"contactName":"7 347 755-97-80 - Входящий звонок","contactPhone":"73477559780","contactCompany":null,"requestedDate":null,"address":null,"comment":"","source":"mango","equipmentTypeHint":null,"isUrgent":false,"externalSourceId":"bitrix-lead-29906"},{"id":29904,"createdAt":1712920038000,"contactName":"7 966 096-64-48 - Входящий звонок","contactPhone":"79660966448","contactCompany":null,"requestedDate":null,"address":null,"comment":"","source":"mango","equipmentTypeHint":null,"isUrgent":false,"externalSourceId":"bitrix-lead-29904"},{"id":29900,"createdAt":1712918437000,"contactName":"7 916 683-15-19 - Входящий звонок","contactPhone":"79166831519","contactCompany":null,"requestedDate":null,"address":null,"comment":"","source":"mango","equipmentTypeHint":null,"isUrgent":false,"externalSourceId":"bitrix-lead-29900"},{"id":29898,"createdAt":1712917959000,"contactName":"7 916 435-79-99 - Входящий звонок","contactPhone":"79164357999","contactCompany":null,"requestedDate":null,"address":null,"comment":"","source":"mango","equipmentTypeHint":null,"isUrgent":false,"externalSourceId":"bitrix-lead-29898"},{"id":29896,"createdAt":1712916865000,"contactName":"Новая заявка Главная","contactPhone":"79037921339","contactCompany":null,"requestedDate":null,"address":null,"comment":"","source":"site","equipmentTypeHint":null,"isUrgent":false,"externalSourceId":"bitrix-lead-29896"},{"id":29894,"createdAt":1712913072000,"contactName":"7 495 718-77-75 - Входящий звонок","contactPhone":"74957187775","contactCompany":null,"requestedDate":null,"address":null,"comment":"","source":"mango","equipmentTypeHint":null,"isUrgent":false,"externalSourceId":"bitrix-lead-29894"},{"id":29888,"createdAt":1712910245000,"contactName":"7 926 918-72-06 - Входящий звонок","contactPhone":"79269187206","contactCompany":null,"requestedDate":null,"address":null,"comment":"","source":"mango","equipmentTypeHint":null,"isUrgent":false,"externalSourceId":"bitrix-lead-29888"},{"id":29884,"createdAt":1712906009000,"contactName":"7 929 550-58-54 - Входящий звонок","contactPhone":"79295505854","contactCompany":null,"requestedDate":null,"address":null,"comment":"","source":"mango","equipmentTypeHint":null,"isUrgent":false,"externalSourceId":"bitrix-lead-29884"},{"id":29882,"createdAt":1712905898000,"contactName":"7 812 245-38-89 - Входящий звонок","contactPhone":"78122453889","contactCompany":null,"requestedDate":null,"address":null,"comment":"","source":"mango","equipmentTypeHint":null,"isUrgent":false,"externalSourceId":"bitrix-lead-29882"},{"id":29880,"createdAt":1712900709000,"contactName":"7 999 178-20-96 - Исходящий звонок","contactPhone":"79991782096","contactCompany":null,"requestedDate":null,"address":null,"comment":"","source":"mango","equipmentTypeHint":null,"isUrgent":false,"externalSourceId":"bitrix-lead-29880"},{"id":29878,"createdAt":1712899952000,"contactName":"7 905 551-70-78 - Входящий звонок","contactPhone":"79055517078","contactCompany":null,"requestedDate":null,"address":null,"comment":"","source":"mango","equipmentTypeHint":null,"isUrgent":false,"externalSourceId":"bitrix-lead-29878"},{"id":29874,"createdAt":1712848306000,"contactName":"7 499 793-37-80 - Входящий звонок","contactPhone":"74997933780","contactCompany":null,"requestedDate":null,"address":null,"comment":"","source":"mango","equipmentTypeHint":null,"isUrgent":false,"externalSourceId":"bitrix-lead-29874"},{"id":29872,"createdAt":1712843648000,"contactName":"7 495 995-11-23 - Входящий звонок","contactPhone":"74959951123","contactCompany":null,"requestedDate":null,"address":null,"comment":"","source":"mango","equipmentTypeHint":null,"isUrgent":false,"externalSourceId":"bitrix-lead-29872"},{"id":29868,"createdAt":1712838946000,"contactName":"Анатолий зак. фура Мск-Челяб","contactPhone":"79186362119","contactCompany":null,"requestedDate":null,"address":null,"comment":"","source":"mango","equipmentTypeHint":null,"isUrgent":false,"externalSourceId":"bitrix-lead-29868"},{"id":29864,"createdAt":1712838162000,"contactName":"7 916 321-27-42 - Входящий звонок","contactPhone":"79163212742","contactCompany":null,"requestedDate":null,"address":null,"comment":"","source":"mango","equipmentTypeHint":null,"isUrgent":false,"externalSourceId":"bitrix-lead-29864"},{"id":29862,"createdAt":1712834914000,"contactName":"7 915 264-27-98 - Входящий звонок","contactPhone":"79152642798","contactCompany":null,"requestedDate":null,"address":null,"comment":"","source":"mango","equipmentTypeHint":null,"isUrgent":false,"externalSourceId":"bitrix-lead-29862"},{"id":29860,"createdAt":1712834273000,"contactName":"7 985 776-69-88 - Входящий звонок","contactPhone":"79857766988","contactCompany":null,"requestedDate":null,"address":null,"comment":"","source":"mango","equipmentTypeHint":null,"isUrgent":false,"externalSourceId":"bitrix-lead-29860"},{"id":29858,"createdAt":1712831975000,"contactName":"7 922 431-00-65 - Входящий звонок","contactPhone":"79224310065","contactCompany":null,"requestedDate":null,"address":null,"comment":"","source":"mango","equipmentTypeHint":null,"isUrgent":false,"externalSourceId":"bitrix-lead-29858"},{"id":29856,"createdAt":1712831730000,"contactName":"7 969 967-24-23 - Входящий звонок","contactPhone":"79699672423","contactCompany":null,"requestedDate":null,"address":null,"comment":"","source":"mango","equipmentTypeHint":null,"isUrgent":false,"externalSourceId":"bitrix-lead-29856"},{"id":29852,"createdAt":1712826460000,"contactName":"7 977 429-56-10 - Исходящий звонок","contactPhone":"79774295610","contactCompany":null,"requestedDate":null,"address":null,"comment":"","source":"mango","equipmentTypeHint":null,"isUrgent":false,"externalSourceId":"bitrix-lead-29852"},{"id":29848,"createdAt":1712820301000,"contactName":"7 985 883-78-00 - Входящий звонок","contactPhone":"79858837800","contactCompany":null,"requestedDate":null,"address":null,"comment":"","source":"mango","equipmentTypeHint":null,"isUrgent":false,"externalSourceId":"bitrix-lead-29848"},{"id":29842,"createdAt":1712766562000,"contactName":"7 968 705-33-69 - Входящий звонок","contactPhone":"79687053369","contactCompany":null,"requestedDate":null,"address":null,"comment":"","source":"mango","equipmentTypeHint":null,"isUrgent":false,"externalSourceId":"bitrix-lead-29842"},{"id":29840,"createdAt":1712765588000,"contactName":"7 986 555-68-88 - Входящий звонок","contactPhone":"79865556888","contactCompany":null,"requestedDate":null,"address":null,"comment":"","source":"mango","equipmentTypeHint":null,"isUrgent":false,"externalSourceId":"bitrix-lead-29840"},{"id":29838,"createdAt":1712759655000,"contactName":"7 919 947-14-48 - Входящий звонок","contactPhone":"79199471448","contactCompany":null,"requestedDate":null,"address":null,"comment":"","source":"mango","equipmentTypeHint":null,"isUrgent":false,"externalSourceId":"bitrix-lead-29838"},{"id":29836,"createdAt":1712758429000,"contactName":"7 929 985-51-87 - Входящий звонок","contactPhone":"79299855187","contactCompany":null,"requestedDate":null,"address":null,"comment":"","source":"mango","equipmentTypeHint":null,"isUrgent":false,"externalSourceId":"bitrix-lead-29836"},{"id":29832,"createdAt":1712757020000,"contactName":"7 903 687-19-73 - Входящий звонок","contactPhone":"79036871973","contactCompany":null,"requestedDate":null,"address":null,"comment":"","source":"mango","equipmentTypeHint":null,"isUrgent":false,"externalSourceId":"bitrix-lead-29832"},{"id":29828,"createdAt":1712754462000,"contactName":"7 916 574-80-14 - Входящий звонок","contactPhone":"79165748014","contactCompany":null,"requestedDate":null,"address":null,"comment":"","source":"mango","equipmentTypeHint":null,"isUrgent":false,"externalSourceId":"bitrix-lead-29828"},{"id":29826,"createdAt":1712754066000,"contactName":"7 905 515-66-88 - Входящий звонок","contactPhone":"79055156688","contactCompany":null,"requestedDate":null,"address":null,"comment":"","source":"mango","equipmentTypeHint":null,"isUrgent":false,"externalSourceId":"bitrix-lead-29826"},{"id":29824,"createdAt":1712753329000,"contactName":"7 341 222-14-62 - Исходящий звонок","contactPhone":"73412221462","contactCompany":null,"requestedDate":null,"address":null,"comment":"","source":"mango","equipmentTypeHint":null,"isUrgent":false,"externalSourceId":"bitrix-lead-29824"},{"id":29820,"createdAt":1712752900000,"contactName":"7 953 551-70-90 - Исходящий звонок","contactPhone":"79535517090","contactCompany":null,"requestedDate":null,"address":null,"comment":"","source":"mango","equipmentTypeHint":null,"isUrgent":false,"externalSourceId":"bitrix-lead-29820"},{"id":29818,"createdAt":1712752735000,"contactName":"7 831 551-70-90 - Исходящий звонок","contactPhone":"78315517090","contactCompany":null,"requestedDate":null,"address":null,"comment":"","source":"mango","equipmentTypeHint":null,"isUrgent":false,"externalSourceId":"bitrix-lead-29818"},{"id":29816,"createdAt":1712752718000,"contactName":"7 831 218-12-74 - Исходящий звонок","contactPhone":"78312181274","contactCompany":null,"requestedDate":null,"address":null,"comment":"","source":"mango","equipmentTypeHint":null,"isUrgent":false,"externalSourceId":"bitrix-lead-29816"},{"id":29812,"createdAt":1712751454000,"contactName":"7 903 792-80-81 - Входящий звонок","contactPhone":"79037928081","contactCompany":null,"requestedDate":null,"address":null,"comment":"","source":"mango","equipmentTypeHint":null,"isUrgent":false,"externalSourceId":"bitrix-lead-29812"},{"id":29810,"createdAt":1712751196000,"contactName":"7 915 150-98-05 - Исходящий звонок","contactPhone":"79151509805","contactCompany":null,"requestedDate":null,"address":null,"comment":"","source":"mango","equipmentTypeHint":null,"isUrgent":false,"externalSourceId":"bitrix-lead-29810"},{"id":29808,"createdAt":1712749853000,"contactName":"7 968 363-61-83 - Входящий звонок","contactPhone":"79683636183","contactCompany":null,"requestedDate":null,"address":null,"comment":"","source":"mango","equipmentTypeHint":null,"isUrgent":false,"externalSourceId":"bitrix-lead-29808"},{"id":29806,"createdAt":1712748697000,"contactName":"7 927 642-71-43 - Входящий звонок","contactPhone":"79276427143","contactCompany":null,"requestedDate":null,"address":null,"comment":"","source":"mango","equipmentTypeHint":null,"isUrgent":false,"externalSourceId":"bitrix-lead-29806"},{"id":29800,"createdAt":1712747048000,"contactName":"7 951 713-65-68 - Исходящий звонок","contactPhone":"79517136568","contactCompany":null,"requestedDate":null,"address":null,"comment":"","source":"mango","equipmentTypeHint":null,"isUrgent":false,"externalSourceId":"bitrix-lead-29800"},{"id":29798,"createdAt":1712746931000,"contactName":"7 962 455-70-82 - Входящий звонок","contactPhone":"79624557082","contactCompany":null,"requestedDate":null,"address":null,"comment":"","source":"mango","equipmentTypeHint":null,"isUrgent":false,"externalSourceId":"bitrix-lead-29798"},{"id":29794,"createdAt":1712746502000,"contactName":"7 965 467-02-96 - Исходящий звонок","contactPhone":"79654670296","contactCompany":null,"requestedDate":null,"address":null,"comment":"","source":"mango","equipmentTypeHint":null,"isUrgent":false,"externalSourceId":"bitrix-lead-29794"},{"id":29790,"createdAt":1712741111000,"contactName":"7 985 152-04-91 - Входящий звонок","contactPhone":"79851520491","contactCompany":null,"requestedDate":null,"address":null,"comment":"","source":"mango","equipmentTypeHint":null,"isUrgent":false,"externalSourceId":"bitrix-lead-29790"},{"id":29788,"createdAt":1712737319000,"contactName":"7 993 485-40-22 - Входящий звонок","contactPhone":"79934854022","contactCompany":null,"requestedDate":null,"address":null,"comment":"","source":"mango","equipmentTypeHint":null,"isUrgent":false,"externalSourceId":"bitrix-lead-29788"},{"id":29786,"createdAt":1712735515000,"contactName":"7 958 412-24-81 - Входящий звонок","contactPhone":"79584122481","contactCompany":null,"requestedDate":null,"address":null,"comment":"","source":"mango","equipmentTypeHint":null,"isUrgent":false,"externalSourceId":"bitrix-lead-29786"},{"id":29784,"createdAt":1712733940000,"contactName":"7 926 016-35-67 - Входящий звонок","contactPhone":"79260163567","contactCompany":null,"requestedDate":null,"address":null,"comment":"","source":"mango","equipmentTypeHint":null,"isUrgent":false,"externalSourceId":"bitrix-lead-29784"},{"id":29778,"createdAt":1712689565000,"contactName":"7 920 752-92-90 - Входящий звонок","contactPhone":"79207529290","contactCompany":null,"requestedDate":null,"address":null,"comment":"","source":"mango","equipmentTypeHint":null,"isUrgent":false,"externalSourceId":"bitrix-lead-29778"},{"id":29776,"createdAt":1712688334000,"contactName":"7 925 112-65-86 - Исходящий звонок","contactPhone":"79251126586","contactCompany":null,"requestedDate":null,"address":null,"comment":"","source":"mango","equipmentTypeHint":null,"isUrgent":false,"externalSourceId":"bitrix-lead-29776"},{"id":29774,"createdAt":1712685738000,"contactName":"7 926 541-66-43 - Входящий звонок","contactPhone":"79265416643","contactCompany":null,"requestedDate":null,"address":null,"comment":"","source":"mango","equipmentTypeHint":null,"isUrgent":false,"externalSourceId":"bitrix-lead-29774"},{"id":29772,"createdAt":1712668719000,"contactName":"7 926 464-54-50 - Входящий звонок","contactPhone":"79264645450","contactCompany":null,"requestedDate":null,"address":null,"comment":"","source":"mango","equipmentTypeHint":null,"isUrgent":false,"externalSourceId":"bitrix-lead-29772"},{"id":29770,"createdAt":1712666643000,"contactName":"7 985 486-58-09 - Входящий звонок","contactPhone":"79854865809","contactCompany":null,"requestedDate":null,"address":null,"comment":"","source":"mango","equipmentTypeHint":null,"isUrgent":false,"externalSourceId":"bitrix-lead-29770"},{"id":29768,"createdAt":1712665331000,"contactName":"7 915 180-39-39 - Входящий звонок","contactPhone":"79151803939","contactCompany":null,"requestedDate":null,"address":null,"comment":"","source":"mango","equipmentTypeHint":null,"isUrgent":false,"externalSourceId":"bitrix-lead-29768"},{"id":29766,"createdAt":1712664691000,"contactName":"7 925 759-31-80 - Исходящий звонок","contactPhone":"79257593180","contactCompany":null,"requestedDate":null,"address":null,"comment":"","source":"mango","equipmentTypeHint":null,"isUrgent":false,"externalSourceId":"bitrix-lead-29766"},{"id":29762,"createdAt":1712657555000,"contactName":"7 991 989-98-34 - Входящий звонок","contactPhone":"79919899834","contactCompany":null,"requestedDate":null,"address":null,"comment":"","source":"mango","equipmentTypeHint":null,"isUrgent":false,"externalSourceId":"bitrix-lead-29762"},{"id":29760,"createdAt":1712652984000,"contactName":"7 909 155-75-11 - Входящий звонок","contactPhone":"79091557511","contactCompany":null,"requestedDate":null,"address":null,"comment":"","source":"mango","equipmentTypeHint":null,"isUrgent":false,"externalSourceId":"bitrix-lead-29760"},{"id":29758,"createdAt":1712652623000,"contactName":"7 903 235-66-76 - Входящий звонок","contactPhone":"79032356676","contactCompany":null,"requestedDate":null,"address":null,"comment":"","source":"mango","equipmentTypeHint":null,"isUrgent":false,"externalSourceId":"bitrix-lead-29758"},{"id":29756,"createdAt":1712650154000,"contactName":"7 966 113-09-19 - Входящий звонок","contactPhone":"79661130919","contactCompany":null,"requestedDate":null,"address":null,"comment":"","source":"mango","equipmentTypeHint":null,"isUrgent":false,"externalSourceId":"bitrix-lead-29756"},{"id":29754,"createdAt":1712648965000,"contactName":"7 912 003-01-27 - Входящий звонок","contactPhone":"79120030127","contactCompany":null,"requestedDate":null,"address":null,"comment":"","source":"mango","equipmentTypeHint":null,"isUrgent":false,"externalSourceId":"bitrix-lead-29754"},{"id":29752,"createdAt":1712648038000,"contactName":"7 963 671-85-56 - Входящий звонок","contactPhone":"79636718556","contactCompany":null,"requestedDate":null,"address":null,"comment":"","source":"mango","equipmentTypeHint":null,"isUrgent":false,"externalSourceId":"bitrix-lead-29752"},{"id":29750,"createdAt":1712589164000,"contactName":"7 968 091-17-77 - Входящий звонок","contactPhone":"79680911777","contactCompany":null,"requestedDate":null,"address":null,"comment":"","source":"mango","equipmentTypeHint":null,"isUrgent":false,"externalSourceId":"bitrix-lead-29750"},{"id":29748,"createdAt":1712588459000,"contactName":"7 965 148-78-50 - Исходящий звонок","contactPhone":"79651487850","contactCompany":null,"requestedDate":null,"address":null,"comment":"","source":"mango","equipmentTypeHint":null,"isUrgent":false,"externalSourceId":"bitrix-lead-29748"},{"id":29746,"createdAt":1712588220000,"contactName":"7 999 800-80-00 - Входящий звонок","contactPhone":"79998008000","contactCompany":null,"requestedDate":null,"address":null,"comment":"","source":"mango","equipmentTypeHint":null,"isUrgent":false,"externalSourceId":"bitrix-lead-29746"},{"id":29744,"createdAt":1712587720000,"contactName":"7 977 583-27-35 - Исходящий звонок","contactPhone":"79775832735","contactCompany":null,"requestedDate":null,"address":null,"comment":"","source":"mango","equipmentTypeHint":null,"isUrgent":false,"externalSourceId":"bitrix-lead-29744"},{"id":29742,"createdAt":1712583995000,"contactName":"7 905 716-71-57 - Исходящий звонок","contactPhone":"79057167157","contactCompany":null,"requestedDate":null,"address":null,"comment":"","source":"mango","equipmentTypeHint":null,"isUrgent":false,"externalSourceId":"bitrix-lead-29742"},{"id":29740,"createdAt":1712580139000,"contactName":"7 985 748-58-59 - Входящий звонок","contactPhone":"79857485859","contactCompany":null,"requestedDate":null,"address":null,"comment":"","source":"mango","equipmentTypeHint":null,"isUrgent":false,"externalSourceId":"bitrix-lead-29740"},{"id":29738,"createdAt":1712579361000,"contactName":"7 960 152-61-31 - Входящий звонок","contactPhone":"79601526131","contactCompany":null,"requestedDate":null,"address":null,"comment":"","source":"mango","equipmentTypeHint":null,"isUrgent":false,"externalSourceId":"bitrix-lead-29738"},{"id":29736,"createdAt":1712578501000,"contactName":"7 939 887-72-94 - Входящий звонок","contactPhone":"79398877294","contactCompany":null,"requestedDate":null,"address":null,"comment":"","source":"mango","equipmentTypeHint":null,"isUrgent":false,"externalSourceId":"bitrix-lead-29736"},{"id":29734,"createdAt":1712575493000,"contactName":"7 906 890-04-09 - Входящий звонок","contactPhone":"79068900409","contactCompany":null,"requestedDate":null,"address":null,"comment":"","source":"mango","equipmentTypeHint":null,"isUrgent":false,"externalSourceId":"bitrix-lead-29734"},{"id":29732,"createdAt":1712572938000,"contactName":"7 919 202-13-50 - Входящий звонок","contactPhone":"79192021350","contactCompany":null,"requestedDate":null,"address":null,"comment":"","source":"mango","equipmentTypeHint":null,"isUrgent":false,"externalSourceId":"bitrix-lead-29732"},{"id":29730,"createdAt":1712569397000,"contactName":"7 906 124-95-89 - Исходящий звонок","contactPhone":"79061249589","contactCompany":null,"requestedDate":null,"address":null,"comment":"","source":"mango","equipmentTypeHint":null,"isUrgent":false,"externalSourceId":"bitrix-lead-29730"},{"id":29728,"createdAt":1712569197000,"contactName":"7 915 741-16-92 - Исходящий звонок","contactPhone":"79157411692","contactCompany":null,"requestedDate":null,"address":null,"comment":"","source":"mango","equipmentTypeHint":null,"isUrgent":false,"externalSourceId":"bitrix-lead-29728"},{"id":29726,"createdAt":1712569178000,"contactName":"7 980 800-47-50 - Входящий звонок","contactPhone":"79808004750","contactCompany":null,"requestedDate":null,"address":null,"comment":"","source":"mango","equipmentTypeHint":null,"isUrgent":false,"externalSourceId":"bitrix-lead-29726"},{"id":29724,"createdAt":1712568978000,"contactName":"7 964 976-16-76 - Исходящий звонок","contactPhone":"79649761676","contactCompany":null,"requestedDate":null,"address":null,"comment":"","source":"mango","equipmentTypeHint":null,"isUrgent":false,"externalSourceId":"bitrix-lead-29724"},{"id":29722,"createdAt":1712568725000,"contactName":"7 903 278-99-23 - Исходящий звонок","contactPhone":"79032789923","contactCompany":null,"requestedDate":null,"address":null,"comment":"","source":"mango","equipmentTypeHint":null,"isUrgent":false,"externalSourceId":"bitrix-lead-29722"},{"id":29720,"createdAt":1712568213000,"contactName":"7 901 492-57-79 - Входящий звонок","contactPhone":"79014925779","contactCompany":null,"requestedDate":null,"address":null,"comment":"","source":"mango","equipmentTypeHint":null,"isUrgent":false,"externalSourceId":"bitrix-lead-29720"},{"id":29718,"createdAt":1712567851000,"contactName":"7 912 332-22-52 - Исходящий звонок","contactPhone":"79123322252","contactCompany":null,"requestedDate":null,"address":null,"comment":"","source":"mango","equipmentTypeHint":null,"isUrgent":false,"externalSourceId":"bitrix-lead-29718"},{"id":29716,"createdAt":1712567447000,"contactName":"7 915 741-15-98 - Исходящий звонок","contactPhone":"79157411598","contactCompany":null,"requestedDate":null,"address":null,"comment":"","source":"mango","equipmentTypeHint":null,"isUrgent":false,"externalSourceId":"bitrix-lead-29716"},{"id":29714,"createdAt":1712567363000,"contactName":"7 985 070-76-15 - Исходящий звонок","contactPhone":"79850707615","contactCompany":null,"requestedDate":null,"address":null,"comment":"","source":"mango","equipmentTypeHint":null,"isUrgent":false,"externalSourceId":"bitrix-lead-29714"},{"id":29712,"createdAt":1712566931000,"contactName":"7 902 585-82-68 - Исходящий звонок","contactPhone":"79025858268","contactCompany":null,"requestedDate":null,"address":null,"comment":"","source":"mango","equipmentTypeHint":null,"isUrgent":false,"externalSourceId":"bitrix-lead-29712"},{"id":29710,"createdAt":1712566911000,"contactName":"7 902 585-26-68 - Исходящий звонок","contactPhone":"79025852668","contactCompany":null,"requestedDate":null,"address":null,"comment":"","source":"mango","equipmentTypeHint":null,"isUrgent":false,"externalSourceId":"bitrix-lead-29710"},{"id":29708,"createdAt":1712561102000,"contactName":"7 925 846-50-29 - Исходящий звонок","contactPhone":"79258465029","contactCompany":null,"requestedDate":null,"address":null,"comment":"","source":"mango","equipmentTypeHint":null,"isUrgent":false,"externalSourceId":"bitrix-lead-29708"},{"id":29706,"createdAt":1712560999000,"contactName":"7 937 076-04-31 - Исходящий звонок","contactPhone":"79370760431","contactCompany":null,"requestedDate":null,"address":null,"comment":"","source":"mango","equipmentTypeHint":null,"isUrgent":false,"externalSourceId":"bitrix-lead-29706"},{"id":29704,"createdAt":1712560551000,"contactName":"7 900 288-76-56 - Входящий звонок","contactPhone":"79002887656","contactCompany":null,"requestedDate":null,"address":null,"comment":"","source":"mango","equipmentTypeHint":null,"isUrgent":false,"externalSourceId":"bitrix-lead-29704"},{"id":29702,"createdAt":1712560128000,"contactName":"7 919 340-05-87 - Исходящий звонок","contactPhone":"79193400587","contactCompany":null,"requestedDate":null,"address":null,"comment":"","source":"mango","equipmentTypeHint":null,"isUrgent":false,"externalSourceId":"bitrix-lead-29702"},{"id":29700,"createdAt":1712559955000,"contactName":"7 922 577-95-55 - Исходящий звонок","contactPhone":"79225779555","contactCompany":null,"requestedDate":null,"address":null,"comment":"","source":"mango","equipmentTypeHint":null,"isUrgent":false,"externalSourceId":"bitrix-lead-29700"},{"id":29698,"createdAt":1712559265000,"contactName":"7 916 806-57-95 - Входящий звонок","contactPhone":"79168065795","contactCompany":null,"requestedDate":null,"address":null,"comment":"","source":"mango","equipmentTypeHint":null,"isUrgent":false,"externalSourceId":"bitrix-lead-29698"},{"id":29696,"createdAt":1712557655000,"contactName":"7 915 213-64-00 - Входящий звонок","contactPhone":"79152136400","contactCompany":null,"requestedDate":null,"address":null,"comment":"","source":"mango","equipmentTypeHint":null,"isUrgent":false,"externalSourceId":"bitrix-lead-29696"},{"id":29694,"createdAt":1712513195000,"contactName":"7 964 539-90-59 - Входящий звонок","contactPhone":"79645399059","contactCompany":null,"requestedDate":null,"address":null,"comment":"","source":"mango","equipmentTypeHint":null,"isUrgent":false,"externalSourceId":"bitrix-lead-29694"},{"id":29690,"createdAt":1712507763000,"contactName":"7 929 979-11-36 - Входящий звонок","contactPhone":"79299791136","contactCompany":null,"requestedDate":null,"address":null,"comment":"","source":"mango","equipmentTypeHint":null,"isUrgent":false,"externalSourceId":"bitrix-lead-29690"},{"id":29688,"createdAt":1712505283000,"contactName":"7 925 778-88-96 - Входящий звонок","contactPhone":"79257788896","contactCompany":null,"requestedDate":null,"address":null,"comment":"","source":"mango","equipmentTypeHint":null,"isUrgent":false,"externalSourceId":"bitrix-lead-29688"},{"id":29686,"createdAt":1712505103000,"contactName":"7 968 609-32-78 - Входящий звонок","contactPhone":"79686093278","contactCompany":null,"requestedDate":null,"address":null,"comment":"","source":"mango","equipmentTypeHint":null,"isUrgent":false,"externalSourceId":"bitrix-lead-29686"},{"id":29684,"createdAt":1712423138000,"contactName":"7 985 345-69-02 - Входящий звонок","contactPhone":"79853456902","contactCompany":null,"requestedDate":null,"address":null,"comment":"","source":"mango","equipmentTypeHint":null,"isUrgent":false,"externalSourceId":"bitrix-lead-29684"},{"id":29674,"createdAt":1712402710000,"contactName":"7 905 114-93-15 - Входящий звонок","contactPhone":"79051149315","contactCompany":null,"requestedDate":null,"address":null,"comment":"","source":"mango","equipmentTypeHint":null,"isUrgent":false,"externalSourceId":"bitrix-lead-29674"},{"id":29672,"createdAt":1712387000000,"contactName":"7 977 636-04-22 - Исходящий звонок","contactPhone":"79776360422","contactCompany":null,"requestedDate":null,"address":null,"comment":"","source":"mango","equipmentTypeHint":null,"isUrgent":false,"externalSourceId":"bitrix-lead-29672"},{"id":29670,"createdAt":1712338940000,"contactName":"7 961 663-51-44 - Исходящий звонок","contactPhone":"79616635144","contactCompany":null,"requestedDate":null,"address":null,"comment":"","source":"mango","equipmentTypeHint":null,"isUrgent":false,"externalSourceId":"bitrix-lead-29670"},{"id":29668,"createdAt":1712327206000,"contactName":"7 925 775-84-61 - Входящий звонок","contactPhone":"79257758461","contactCompany":null,"requestedDate":null,"address":null,"comment":"","source":"mango","equipmentTypeHint":null,"isUrgent":false,"externalSourceId":"bitrix-lead-29668"}]}